csv2img/__init__.py
csv2img/csv2img.py
csv2img-1.0.0.dist-info/METADATA
csv2img-1.0.0.dist-info/WHEEL
csv2img-1.0.0.dist-info/top_level.txt
csv2img-1.0.0.dist-info/RECORD
