Metadata-Version: 2.1
Name: csv2img
Version: 1.0.0
Summary: Package to save CSV as PNG
Home-page: https://github.com/Shun-Calvin/csv2img.git
Author: Shun-Calvin
Author-email: 5u80w7c15@mozmail.com
License: UNKNOWN
Platform: UNKNOWN
Classifier: Programming Language :: Python :: 3
Classifier: License :: OSI Approved :: MIT License
Classifier: Operating System :: OS Independent
Requires-Python: >=3.4
Requires-Dist: csv2pdf (~=0.1.4)
Requires-Dist: fitz (~=0.0.1.dev2)
Requires-Dist: PyMuPDF (~=1.21.1)
